knocker.py
knocker-0.1.4.dist-info/DESCRIPTION.rst
knocker-0.1.4.dist-info/METADATA
knocker-0.1.4.dist-info/RECORD
knocker-0.1.4.dist-info/WHEEL
knocker-0.1.4.dist-info/entry_points.txt
knocker-0.1.4.dist-info/metadata.json
knocker-0.1.4.dist-info/top_level.txt
