Metadata-Version: 2.0
Name: knocker
Version: 0.1.4
Summary: Port knocking client
Home-page: http://github.com/rougeh/knocker
Author: Marco Rougeth
Author-email: marco@rougeth.com
License: UNKNOWN
Platform: UNKNOWN
